data/__init__.py
data/numpysocket.py
data/remoteh5.py
data/utility.py
dnn/__init__.py
dnn/ednn.py
dnn/english_muffin.py
kyle_helper/__init__.py
kyle_helper/data/__init__.py
kyle_helper/data/numpysocket.py
kyle_helper/data/remoteh5.py
kyle_helper/data/utility.py
kyle_helper/dnn/__init__.py
kyle_helper/dnn/ednn.py
kyle_helper/dnn/english_muffin.py
kyle_helper/latex/__init__.py
kyle_helper/latex/results.py
kyle_helper/render/__init__.py
kyle_helper/render/moviemaker.py
kyle_helper-1.3.0.data/scripts/update_result
kyle_helper-1.3.0.dist-info/METADATA
kyle_helper-1.3.0.dist-info/RECORD
kyle_helper-1.3.0.dist-info/WHEEL
kyle_helper-1.3.0.dist-info/top_level.txt
latex/__init__.py
latex/results.py
render/__init__.py
render/moviemaker.py
