Metadata-Version: 2.1
Name: kyle-helper
Version: 1.3.0
Summary: Helper functions to help Kyle
Home-page: UNKNOWN
Author: Kyle Mills
Author-email: kyle.mills@uoit.net
License: UNKNOWN
Platform: UNKNOWN
Requires-Dist: inflect
Requires-Dist: regex
Requires-Dist: argparse
Requires-Dist: matplotlib
Requires-Dist: opencv-python
Requires-Dist: numpy
